bsif_webview2-1.5.0.dist-info/licenses/LICENSE
webview/BSIF.WebView2Bridge.dll
webview/Microsoft.Web.WebView2.Core.dll
webview/Microsoft.Web.WebView2.WinForms.dll
webview/__init__.py
webview/bridge.js
webview/bridge.py
webview/enviroment.py
webview/handlers.py
webview/webview.py
webview/runtimes/win-arm64/native/WebView2Loader.dll
webview/runtimes/win-x64/native/WebView2Loader.dll
webview/runtimes/win-x86/native/WebView2Loader.dll
bsif_webview2-1.5.0.dist-info/METADATA
bsif_webview2-1.5.0.dist-info/WHEEL
bsif_webview2-1.5.0.dist-info/top_level.txt
bsif_webview2-1.5.0.dist-info/RECORD
